zbackup/__init__.py
zbackup/backup.py
zbackup/gcs.py
zbackup/main.py
z_backup-0.1.1.dist-info/METADATA
z_backup-0.1.1.dist-info/WHEEL
z_backup-0.1.1.dist-info/entry_points.txt
z_backup-0.1.1.dist-info/RECORD
