Metadata-Version: 2.1
Name: z-backup
Version: 0.1.1
Summary: Simple backup service
Author: Wenyu Zhao
Author-email: wenyuzhaox@gmail.com
Requires-Python: >=3.12,<4.0
Classifier: Programming Language :: Python :: 3
Classifier: Programming Language :: Python :: 3.12
Requires-Dist: google-cloud-storage (>=2.18.2,<3.0.0)
Requires-Dist: python-dotenv (>=1.0.1,<2.0.0)
Requires-Dist: schedule (>=1.2.2,<2.0.0)
Requires-Dist: setuptools (>=72.1.0,<73.0.0)
Requires-Dist: typer (>=0.12.3,<0.13.0)
